vnpy_emt/__init__.py
vnpy_emt/api/__init__.py
vnpy_emt/api/emt_api.dll
vnpy_emt/api/emt_constant.py
vnpy_emt/api/emt_quote_api.dll
vnpy_emt/api/emt_trader_api_c.dll
vnpy_emt/api/vnemtmd.cp310-win_amd64.pyd
vnpy_emt/api/vnemttd.cp310-win_amd64.pyd
vnpy_emt/api/generator/emt_md_header_function.h
vnpy_emt/api/generator/emt_md_header_on.h
vnpy_emt/api/generator/emt_md_source_callback.cpp
vnpy_emt/api/generator/emt_md_source_function.cpp
vnpy_emt/api/generator/emt_md_source_module.cpp
vnpy_emt/api/generator/emt_md_source_on.cpp
vnpy_emt/api/generator/emt_td_header_function.h
vnpy_emt/api/generator/emt_td_header_on.h
vnpy_emt/api/generator/emt_td_source_callback.cpp
vnpy_emt/api/generator/emt_td_source_function.cpp
vnpy_emt/api/generator/emt_td_source_module.cpp
vnpy_emt/api/generator/emt_td_source_on.cpp
vnpy_emt/api/include/emt/emt_api.h
vnpy_emt/api/include/emt/emt_api_data_type.h
vnpy_emt/api/include/emt/emt_api_struct.h
vnpy_emt/api/include/emt/emt_api_struct_common.h
vnpy_emt/api/include/emt/emt_quote_api.h
vnpy_emt/api/include/emt/emt_quote_struct.h
vnpy_emt/api/include/emt/emt_trader_api.h
vnpy_emt/api/include/emt/eoms_api_fund_struct.h
vnpy_emt/api/include/emt/eoms_api_struct.h
vnpy_emt/api/include/pybind11/attr.h
vnpy_emt/api/include/pybind11/buffer_info.h
vnpy_emt/api/include/pybind11/cast.h
vnpy_emt/api/include/pybind11/chrono.h
vnpy_emt/api/include/pybind11/common.h
vnpy_emt/api/include/pybind11/complex.h
vnpy_emt/api/include/pybind11/eigen.h
vnpy_emt/api/include/pybind11/embed.h
vnpy_emt/api/include/pybind11/eval.h
vnpy_emt/api/include/pybind11/functional.h
vnpy_emt/api/include/pybind11/iostream.h
vnpy_emt/api/include/pybind11/numpy.h
vnpy_emt/api/include/pybind11/operators.h
vnpy_emt/api/include/pybind11/options.h
vnpy_emt/api/include/pybind11/pybind11.h
vnpy_emt/api/include/pybind11/pytypes.h
vnpy_emt/api/include/pybind11/stl.h
vnpy_emt/api/include/pybind11/stl_bind.h
vnpy_emt/api/include/pybind11/detail/class.h
vnpy_emt-2.10.0.dist-info/LICENSE
vnpy_emt-2.10.0.dist-info/METADATA
vnpy_emt-2.10.0.dist-info/WHEEL
vnpy_emt-2.10.0.dist-info/top_level.txt
vnpy_emt-2.10.0.dist-info/RECORD
